ChinesePatentParser/__init__.py
ChinesePatentParser/general_parser.py
ChinesePatentParser/patent_instance.py
ChinesePatentParser/patent_parser.py
ChinesePatentParser/patent_template.py
ChinesePatentParser/simple_bidict.py
tests/__init__.py
tests/test.py
ChinesePatentParser-1.0.dist-info/LICENSE
ChinesePatentParser-1.0.dist-info/METADATA
ChinesePatentParser-1.0.dist-info/WHEEL
ChinesePatentParser-1.0.dist-info/top_level.txt
ChinesePatentParser-1.0.dist-info/RECORD
