Metadata-Version: 2.1
Name: ChinesePatentParser
Version: 1.0
Summary: A Python script that can parse a Chinese patent of invention type to extract fields, sections, and subsections in it.
Home-page: https://github.com/msmarkgu/ChinesePatentParser
Author: Mark Gu
Author-email: mark.reachee@gmail.com
Classifier: Programming Language :: Python :: 3
Classifier: License :: OSI Approved :: MIT License
Classifier: Operating System :: OS Independent
Requires-Python: >=3.8
License-File: LICENSE
Requires-Dist: pdfplumber
